sunnbear/__init__.py
sunnbear/dummy.py
sunnbear-0.0.2.dist-info/METADATA
sunnbear-0.0.2.dist-info/WHEEL
sunnbear-0.0.2.dist-info/licenses/LICENSE
sunnbear-0.0.2.dist-info/RECORD
