Metadata-Version: 2.4
Name: sunnbear
Version: 0.0.2
Summary: /
Project-URL: Source, https://github.com/bertpl/sunnbear
Project-URL: ChangeLog, https://github.com/bertpl/sunnbear/blob/main/CHANGELOG.md
Project-URL: Issues, https://github.com/bertpl/sunnbear/issues
Project-URL: Roadmap, https://github.com/bertpl/sunnbear/milestones
Author-email: Bert Pluymers <bert.pluymers@gmail.com>
License-File: LICENSE
Requires-Python: >=3.11
Requires-Dist: counted-float>=1.0.0
Requires-Dist: matplotlib>=3.5.0
Requires-Dist: max-div>=0.0.1
Requires-Dist: mpl-composite>=0.0.1
Requires-Dist: numba>=0.58.0
Requires-Dist: numpy>=1.20
Requires-Dist: snuffled>=0.0.1
